<?xml version="1.0" encoding="utf-8" ?>
<dwsync>
<file name="file.gif" server="C:/xampp/htdocs/clinica/" local="130250095860416828" remote="130250095860000000" Dst="1" />
<file name="folder-closed.gif" server="C:/xampp/htdocs/clinica/" local="130250095860616839" remote="130250095860000000" Dst="1" />
<file name="folder.gif" server="C:/xampp/htdocs/clinica/" local="130250095860816851" remote="130250095860000000" Dst="1" />
<file name="minus.gif" server="C:/xampp/htdocs/clinica/" local="130250095861026863" remote="130250095860000000" Dst="1" />
<file name="plus.gif" server="C:/xampp/htdocs/clinica/" local="130250095861226874" remote="130250095860000000" Dst="1" />
<file name="treeview-black-line.gif" server="C:/xampp/htdocs/clinica/" local="130250095861426886" remote="130250095860000000" Dst="1" />
<file name="treeview-black.gif" server="C:/xampp/htdocs/clinica/" local="130250095861626897" remote="130250095860000000" Dst="1" />
<file name="treeview-default-line.gif" server="C:/xampp/htdocs/clinica/" local="130250095861836909" remote="130250095860000000" Dst="1" />
<file name="treeview-default.gif" server="C:/xampp/htdocs/clinica/" local="130250095862046921" remote="130250095860000000" Dst="1" />
<file name="treeview-famfamfam-line.gif" server="C:/xampp/htdocs/clinica/" local="130250095862246933" remote="130250095860000000" Dst="1" />
<file name="treeview-famfamfam.gif" server="C:/xampp/htdocs/clinica/" local="130250095862456945" remote="130250095860000000" Dst="1" />
<file name="treeview-gray-line.gif" server="C:/xampp/htdocs/clinica/" local="130250095862656956" remote="130250095860000000" Dst="1" />
<file name="treeview-gray.gif" server="C:/xampp/htdocs/clinica/" local="130250095862866968" remote="130250095860000000" Dst="1" />
<file name="treeview-red-line.gif" server="C:/xampp/htdocs/clinica/" local="130250095863066980" remote="130250095860000000" Dst="1" />
<file name="treeview-red.gif" server="C:/xampp/htdocs/clinica/" local="130250095863276992" remote="130250095860000000" Dst="1" />
</dwsync>