<?xml version="1.0" encoding="utf-8" ?>
<dwsync>
<file name="calendar_lang.php" server="C:/xampp/htdocs/clinica/" local="130250096171804638" remote="130250096170000000" Dst="1" />
<file name="date_lang.php" server="C:/xampp/htdocs/clinica/" local="130250096172044652" remote="130250096170000000" Dst="1" />
<file name="db_lang.php" server="C:/xampp/htdocs/clinica/" local="130250096172314668" remote="130250096170000000" Dst="1" />
<file name="email_lang.php" server="C:/xampp/htdocs/clinica/" local="130250096172534680" remote="130250096170000000" Dst="1" />
<file name="form_validation_lang.php" server="C:/xampp/htdocs/clinica/" local="130250096172744692" remote="130250096170000000" Dst="1" />
<file name="ftp_lang.php" server="C:/xampp/htdocs/clinica/" local="130250096172964705" remote="130250096170000000" Dst="1" />
<file name="imglib_lang.php" server="C:/xampp/htdocs/clinica/" local="130250096173184717" remote="130250096170000000" Dst="1" />
<file name="migration_lang.php" server="C:/xampp/htdocs/clinica/" local="130250096173424731" remote="130250096170000000" Dst="1" />
<file name="number_lang.php" server="C:/xampp/htdocs/clinica/" local="130250096173654744" remote="130250096170000000" Dst="1" />
<file name="profiler_lang.php" server="C:/xampp/htdocs/clinica/" local="130250096173874757" remote="130250096170000000" Dst="1" />
<file name="unit_test_lang.php" server="C:/xampp/htdocs/clinica/" local="130250096174094769" remote="130250096170000000" Dst="1" />
<file name="upload_lang.php" server="C:/xampp/htdocs/clinica/" local="130250096174314782" remote="130250096170000000" Dst="1" />
<file name="calendar_lang.php" server="clincadentalsantarafaela.herobo.com" local="130250096171804638" remote="130277620200000000" Dst="1" />
<file name="date_lang.php" server="clincadentalsantarafaela.herobo.com" local="130250096172044652" remote="130277620200000000" Dst="1" />
<file name="db_lang.php" server="clincadentalsantarafaela.herobo.com" local="130250096172314668" remote="130277620200000000" Dst="1" />
<file name="email_lang.php" server="clincadentalsantarafaela.herobo.com" local="130250096172534680" remote="130277620200000000" Dst="1" />
<file name="form_validation_lang.php" server="clincadentalsantarafaela.herobo.com" local="130250096172744692" remote="130277620200000000" Dst="1" />
<file name="ftp_lang.php" server="clincadentalsantarafaela.herobo.com" local="130250096172964705" remote="130277620200000000" Dst="1" />
<file name="imglib_lang.php" server="clincadentalsantarafaela.herobo.com" local="130250096173184717" remote="130277620200000000" Dst="1" />
<file name="migration_lang.php" server="clincadentalsantarafaela.herobo.com" local="130250096173424731" remote="130277620200000000" Dst="1" />
<file name="number_lang.php" server="clincadentalsantarafaela.herobo.com" local="130250096173654744" remote="130277620200000000" Dst="1" />
<file name="profiler_lang.php" server="clincadentalsantarafaela.herobo.com" local="130250096173874757" remote="130277620200000000" Dst="1" />
<file name="unit_test_lang.php" server="clincadentalsantarafaela.herobo.com" local="130250096174094769" remote="130277620200000000" Dst="1" />
<file name="upload_lang.php" server="clincadentalsantarafaela.herobo.com" local="130250096174314782" remote="130277620200000000" Dst="1" />
</dwsync>